{
  "sea_level": 0,
  "disable_mob_generation": false,
  "aquifers_enabled": false,
  "ore_veins_enabled": true,
  "legacy_random_source": false,
  "default_block": {
    "name": "minecraft:crying_obsidian"
  },
  "default_fluid": {
    "name": "minecraft:lava"
  },
  "noise": {
    "min_y": 0,
    "height": 256,
    "size_horizontal": 4,
    "size_vertical": 4,
    "sampling": {
      "xz_scale": 10.0,
      "y_scale": 0.01,
      "xz_factor": 1.0,
      "y_factor": 1.0
    },
    "terrain_shaper": {
      "offset": 0.0,
      "factor": 0.0,
      "jaggedness": 100.0
    }
  },
  "noise_router": {
    "barrier": 0,
    "fluid_level_floodedness": 0,
    "fluid_level_spread": 0,
    "lava": 0,
    "vein_toggle": 0,
    "vein_ridyness": 0,
    "vein_gap": 0,
    "temperature": 0,
    "vegetation": 0,
    "continents": 0,
    "erosion": 0,
    "depth": 0,
    "ridges": 0,
    "initial_density_without_jaggedness": 1,
    "final_density": {
      "type": "minecraft:noise",
      "noise": "minecraft:nether",
      "xz_scale": 100.0,
      "y_scale": 1.0
    }
  },
  "surface_rule": {
    "type": "minecraft:block",
    "result_state": {
      "name": "minecraft:gilded_blackstone"
    }
  }
}
